<TQSOptionContentRecord.DefaultTurretSubTargetContent __type="TQSOptionContentRecord" __ref="2b85b16c-1e66-43c1-ac92-b278a01727c0" __path="libs/foundry/records/tacticalquery/ttsqueries/content/defaultturretsubtargetcontent.xml">
  <content __type="TQSOptionContent">
    <parameters>
      <TQSInputFloatValue condition="maximumRecentDamage" value="5000" __type="TQSInput" __polymorphicType="TQSInputFloatValue">
        <requirements __type="TagsDNF">
          <terms />
        </requirements>
        <overrides />
      </TQSInputFloatValue>
    </parameters>
    <generation>
      <TQSInputFloatValue condition="attachedTargetables_around_referencePoint" value="0" __type="TQSInput" __polymorphicType="TQSInputFloatValue">
        <requirements __type="TagsDNF">
          <terms />
        </requirements>
        <overrides />
      </TQSInputFloatValue>
    </generation>
    <conditions>
      <TQSInputBoolValue condition="isAlive" value="1" __type="TQSInput" __polymorphicType="TQSInputBoolValue">
        <requirements __type="TagsDNF">
          <terms />
        </requirements>
        <overrides />
      </TQSInputBoolValue>
    </conditions>
    <weights>
      <TQSWeightInputValue condition="attackerScoreToCapacityRatioExcluding_the_entity" weight="-1" __type="TQSInput" __polymorphicType="TQSWeightInputValue">
        <requirements __type="TagsDNF">
          <terms />
        </requirements>
        <overrides />
      </TQSWeightInputValue>
      <TQSWeightInputValue condition="damageDealtAsAPortionOfHealth_to_host" weight="1" __type="TQSInput" __polymorphicType="TQSWeightInputValue">
        <requirements __type="TagsDNF">
          <terms />
        </requirements>
        <overrides />
      </TQSWeightInputValue>
      <TQSWeightInputValue condition="totalRecentDamageDealt" weight="1" __type="TQSInput" __polymorphicType="TQSWeightInputValue">
        <requirements __type="TagsDNF">
          <terms />
        </requirements>
        <overrides />
      </TQSWeightInputValue>
    </weights>
  </content>
</TQSOptionContentRecord.DefaultTurretSubTargetContent>