<MissionBrokerEntry.PU_DestroyNarcotics_legal_Stanton4_H notForRelease="0" missionModule="libs/subsumption/missions/pu/pu_missions/ugf/pu_destroy_stash.xml" title="@mtps_UGF_destroy_H_title_001" titleHUD="@LOC_UNINITIALIZED" description="@mtps_UGF_destroy_H_desc_001" missionGiver="@mtps_from" commsChannelName="@LOC_UNINITIALIZED" type="62f92440-202a-43d3-9cb8-b917d4e4a102" locationMissionAvailable="00000000-0000-0000-0000-000000000000" notifyOnAvailable="0" showAsOffer="0" missionBuyInAmount="0" refundBuyInOnWithdraw="0" hasCompleteButton="0" handlesAbandonRequest="0" missionModulePerPlayer="1" maxInstances="1" maxPlayersPerInstance="1" maxInstancesPerPlayer="1" canBeShared="1" onceOnly="0" displayAlliedMarkers="1" availableInPrison="0" failIfSentToPrison="1" requestOnly="0" respawnTime="0" respawnTimeVariation="0" instanceHasLifeTime="1" showLifeTimeInMobiGlas="0" instanceLifeTime="15" instanceLifeTimeVariation="0" canReacceptAfterAbandoning="0" abandonedCooldownTime="10" abandonedCooldownTimeVariation="5" canReacceptAfterFailing="0" hasPersonalCooldown="1" personalCooldownTime="5" personalCooldownTimeVariation="5" moduleHandlesOwnShutdown="0" linkedMission="00000000-0000-0000-0000-000000000000" lawfulMission="1" missionGiverRecord="bfb177af-0724-47b6-b49e-62cf85300484" invitationMission="00000000-0000-0000-0000-000000000000" missionGiverFragmentTags="" __type="MissionBrokerEntry" __ref="2d18bbd8-70f1-449c-b3df-52f20ea07517" __path="libs/foundry/records/missionbroker/pu_missions/infiltrateanddefend/pu_destroynarcotics_legal_stanton4_h.xml">
  <availableDateSchedule />
  <missionReward reward="75000" max="0" plusBonuses="1" currencyType="UEC" reputationBonus="00000000-0000-0000-0000-000000000000" __type="MissionReward" />
  <missionResultReputationRewards>
    <SReputationAmountListParams __type="SReputationAmountListParams">
      <reputationAmounts>
        <SReputationAmountParams uniqueEntityClass="6a02d369-8ac2-4df8-9d68-f075d58bb906" reputationScope="e23f8034-3e76-49b3-bfc6-228bcb1381df" reward="1335b737-6188-4c21-8923-98a74bcd3071" __type="SReputationAmountParams" />
        <SReputationAmountParams uniqueEntityClass="6a02d369-8ac2-4df8-9d68-f075d58bb906" reputationScope="f340b011-c40c-4229-b9c1-ce6a3eb1df77" reward="ca6ddd8e-6995-4deb-9914-6e7020404028" __type="SReputationAmountParams" />
      </reputationAmounts>
    </SReputationAmountListParams>
    <SReputationAmountListParams __type="SReputationAmountListParams">
      <reputationAmounts>
        <SReputationAmountParams uniqueEntityClass="6a02d369-8ac2-4df8-9d68-f075d58bb906" reputationScope="e23f8034-3e76-49b3-bfc6-228bcb1381df" reward="4ad8855c-862d-4681-bebb-99ac160cb7b0" __type="SReputationAmountParams" />
        <SReputationAmountParams uniqueEntityClass="6a02d369-8ac2-4df8-9d68-f075d58bb906" reputationScope="f340b011-c40c-4229-b9c1-ce6a3eb1df77" reward="d0ad40da-5ae0-4c39-bc1a-d1b276dbe2ca" __type="SReputationAmountParams" />
      </reputationAmounts>
    </SReputationAmountListParams>
    <SReputationAmountListParams __type="SReputationAmountListParams">
      <reputationAmounts>
        <SReputationAmountParams uniqueEntityClass="6a02d369-8ac2-4df8-9d68-f075d58bb906" reputationScope="e23f8034-3e76-49b3-bfc6-228bcb1381df" reward="506f39e7-7d9a-4ec7-a74e-c1f5b47e58d7" __type="SReputationAmountParams" />
        <SReputationAmountParams uniqueEntityClass="6a02d369-8ac2-4df8-9d68-f075d58bb906" reputationScope="f340b011-c40c-4229-b9c1-ce6a3eb1df77" reward="506f39e7-7d9a-4ec7-a74e-c1f5b47e58d7" __type="SReputationAmountParams" />
      </reputationAmounts>
    </SReputationAmountListParams>
  </missionResultReputationRewards>
  <journalEntriesToAddOnComplete />
  <journalEntriesToRemoveOnComplete />
  <completionTags __type="TagList">
    <tags />
  </completionTags>
  <modifiers />
  <missionTags />
  <reputationPrerequisites wantedLevelJurisdictionOverride="00000000-0000-0000-0000-000000000000" __type="ReputationPrerequisites">
    <wantedLevel minValue="0" maxValue="0" __type="ReputationPrerequisiteRange" />
  </reputationPrerequisites>
  <reputationRequirements>
    <SReputationMissionRequirementsParams __type="SReputationMissionRequirementsParams">
      <expression>
        <SReputationMissionGiverRequirementParams missionGiverEntityClass="6a02d369-8ac2-4df8-9d68-f075d58bb906" reputationScope="e23f8034-3e76-49b3-bfc6-228bcb1381df" comparison="GreaterThanOrEqualTo" standing="de7aefe9-2265-48ab-a8f8-125e086a938e" __type="SReputationMissionRequirementExpressionElement" __polymorphicType="SReputationMissionGiverRequirementParams" />
      </expression>
    </SReputationMissionRequirementsParams>
  </reputationRequirements>
  <requiredMissions />
  <requiredCompletedMissionTags />
  <requiredJournalEntries />
  <properties>
    <MissionProperty missionVariableName="MDSE_UGF" extendedTextToken="Location" __type="MissionProperty">
      <value>
        <MissionPropertyValue_Location minLocationsToFind="1" maxLocationsToFind="1" debugForceChosenLocation="00000000-0000-0000-0000-000000000000" __type="BaseMissionPropertyValue" __polymorphicType="MissionPropertyValue_Location">
          <matchConditions>
            <DataSetMatchCondition_TagSearch tagType="General" __type="BaseDataSetMatchCondition" __polymorphicType="DataSetMatchCondition_TagSearch">
              <tagSearch>
                <TagSearchTerm __type="TagSearchTerm">
                  <positiveTags>
                    <Reference value="1dcaf9e0-9b99-4c2d-83e3-faba4ef7673a" />
                    <Reference value="cb4d4877-645c-4450-a166-224a129c3d4c" />
                    <Reference value="ff4d704a-7840-4577-ba64-7d4bd709ab9d" />
                  </positiveTags>
                  <negativeTags>
                    <Reference value="d5d68f8c-005a-439b-91ee-3ce637306d09" />
                  </negativeTags>
                </TagSearchTerm>
              </tagSearch>
            </DataSetMatchCondition_TagSearch>
          </matchConditions>
          <resourceTags>
            <Reference value="71ab54b9-727e-49e7-92a7-20f2812c1926" />
          </resourceTags>
        </MissionPropertyValue_Location>
      </value>
    </MissionProperty>
    <MissionProperty missionVariableName="MB_I_FlatRate" extendedTextToken="" __type="MissionProperty">
      <value>
        <MissionPropertyValue_Integer __type="BaseMissionPropertyValue" __polymorphicType="MissionPropertyValue_Integer">
          <options>
            <MissionPropertyValueOption_Integer textId="@LOC_UNINITIALIZED" weighting="1" DEBUG_forceChooseThisOption="0" value="4000" variation="0" __type="BaseMissionPropertyValueOption" __polymorphicType="MissionPropertyValueOption_Integer">
              <dependentProperties />
            </MissionPropertyValueOption_Integer>
          </options>
        </MissionPropertyValue_Integer>
      </value>
    </MissionProperty>
    <MissionProperty missionVariableName="MB_I_HighValueRate" extendedTextToken="" __type="MissionProperty">
      <value>
        <MissionPropertyValue_Integer __type="BaseMissionPropertyValue" __polymorphicType="MissionPropertyValue_Integer">
          <options>
            <MissionPropertyValueOption_Integer textId="@LOC_UNINITIALIZED" weighting="1" DEBUG_forceChooseThisOption="0" value="400" variation="0" __type="BaseMissionPropertyValueOption" __polymorphicType="MissionPropertyValueOption_Integer">
              <dependentProperties />
            </MissionPropertyValueOption_Integer>
          </options>
        </MissionPropertyValue_Integer>
      </value>
    </MissionProperty>
    <MissionProperty missionVariableName="MB_I_MediumValueRate" extendedTextToken="" __type="MissionProperty">
      <value>
        <MissionPropertyValue_Integer __type="BaseMissionPropertyValue" __polymorphicType="MissionPropertyValue_Integer">
          <options>
            <MissionPropertyValueOption_Integer textId="@LOC_UNINITIALIZED" weighting="1" DEBUG_forceChooseThisOption="0" value="200" variation="0" __type="BaseMissionPropertyValueOption" __polymorphicType="MissionPropertyValueOption_Integer">
              <dependentProperties />
            </MissionPropertyValueOption_Integer>
          </options>
        </MissionPropertyValue_Integer>
      </value>
    </MissionProperty>
    <MissionProperty missionVariableName="MB_I_LowValueRae" extendedTextToken="" __type="MissionProperty">
      <value>
        <MissionPropertyValue_Integer __type="BaseMissionPropertyValue" __polymorphicType="MissionPropertyValue_Integer">
          <options>
            <MissionPropertyValueOption_Integer textId="@LOC_UNINITIALIZED" weighting="1" DEBUG_forceChooseThisOption="0" value="100" variation="0" __type="BaseMissionPropertyValueOption" __polymorphicType="MissionPropertyValueOption_Integer">
              <dependentProperties />
            </MissionPropertyValueOption_Integer>
          </options>
        </MissionPropertyValue_Integer>
      </value>
    </MissionProperty>
    <MissionProperty missionVariableName="" extendedTextToken="Contractor" __type="MissionProperty">
      <value>
        <MissionPropertyValue_Organization debugForceChosenOrganization="00000000-0000-0000-0000-000000000000" __type="BaseMissionPropertyValue" __polymorphicType="MissionPropertyValue_Organization">
          <matchConditions>
            <DataSetMatchCondition_SpecificOrganizationsDef __type="BaseDataSetMatchCondition" __polymorphicType="DataSetMatchCondition_SpecificOrganizationsDef">
              <organizations>
                <Reference value="9bfded5a-c844-43d6-9a40-1052916ea7a2" />
              </organizations>
            </DataSetMatchCondition_SpecificOrganizationsDef>
          </matchConditions>
        </MissionPropertyValue_Organization>
      </value>
    </MissionProperty>
    <MissionProperty missionVariableName="MissionType" extendedTextToken="" __type="MissionProperty">
      <value>
        <MissionPropertyValue_StringHash __type="BaseMissionPropertyValue" __polymorphicType="MissionPropertyValue_StringHash">
          <options>
            <MissionPropertyValueOption_StringHash textId="@LOC_UNINITIALIZED" weighting="1" DEBUG_forceChooseThisOption="0" value="PVE" __type="BaseMissionPropertyValueOption" __polymorphicType="MissionPropertyValueOption_StringHash">
              <dependentProperties />
            </MissionPropertyValueOption_StringHash>
          </options>
        </MissionPropertyValue_StringHash>
      </value>
    </MissionProperty>
    <MissionProperty missionVariableName="Property_AllowEmergentAI" extendedTextToken="" __type="MissionProperty">
      <value>
        <MissionPropertyValue_Integer __type="BaseMissionPropertyValue" __polymorphicType="MissionPropertyValue_Integer">
          <options>
            <MissionPropertyValueOption_Integer textId="@LOC_UNINITIALIZED" weighting="1" DEBUG_forceChooseThisOption="0" value="0" variation="0" __type="BaseMissionPropertyValueOption" __polymorphicType="MissionPropertyValueOption_Integer">
              <dependentProperties />
            </MissionPropertyValueOption_Integer>
          </options>
        </MissionPropertyValue_Integer>
      </value>
    </MissionProperty>
    <MissionProperty missionVariableName="Property_SpawnDescriptions" extendedTextToken="" __type="MissionProperty">
      <value>
        <MissionPropertyValue_NPCSpawnDescriptions __type="BaseMissionPropertyValue" __polymorphicType="MissionPropertyValue_NPCSpawnDescriptions">
          <spawnDescriptions>
            <SpawnDescription_NPCGroup priority="-1" includeLocationAISpawnTags="0" __type="SpawnDescription_NPCGroup">
              <autoSpawnSettings initialActivity="" minGroupSize="2" maxGroupSize="4" maxConcurrentSpawns="4" maxSpawns="4" minSpawnDelay="-1" maxSpawnDelay="-1" missionAlliedMarker="0" __type="AutoSpawnSettings">
                <positiveCharacterTags __type="TagList">
                  <tags>
                    <Reference value="0b879772-f9e0-4976-9ad9-d2b4223e147e" />
                    <Reference value="9279f704-6eb3-4ffe-a186-19811f147b1d" />
                    <Reference value="dffd6f5e-dea7-48e4-9d23-ec436b6f0153" />
                  </tags>
                </positiveCharacterTags>
                <negativeCharacterTags __type="TagList">
                  <tags />
                </negativeCharacterTags>
                <inventoryItems />
                <closetPositiveTags __type="TagList">
                  <tags />
                </closetPositiveTags>
                <closetNegativeTags __type="TagList">
                  <tags />
                </closetNegativeTags>
              </autoSpawnSettings>
              <identifierTags __type="TagList">
                <tags />
              </identifierTags>
            </SpawnDescription_NPCGroup>
            <SpawnDescription_NPCGroup priority="-1" includeLocationAISpawnTags="0" __type="SpawnDescription_NPCGroup">
              <autoSpawnSettings initialActivity="" minGroupSize="2" maxGroupSize="2" maxConcurrentSpawns="2" maxSpawns="4" minSpawnDelay="5" maxSpawnDelay="5" missionAlliedMarker="0" __type="AutoSpawnSettings">
                <positiveCharacterTags __type="TagList">
                  <tags>
                    <Reference value="bd6b903f-0d2d-4688-8329-db68c16fb0d1" />
                    <Reference value="ecfb92fe-5d2d-4fef-aa8f-2f09fcf42b6f" />
                  </tags>
                </positiveCharacterTags>
                <negativeCharacterTags __type="TagList">
                  <tags />
                </negativeCharacterTags>
                <inventoryItems />
                <closetPositiveTags __type="TagList">
                  <tags />
                </closetPositiveTags>
                <closetNegativeTags __type="TagList">
                  <tags />
                </closetNegativeTags>
              </autoSpawnSettings>
              <identifierTags __type="TagList">
                <tags />
              </identifierTags>
            </SpawnDescription_NPCGroup>
            <SpawnDescription_NPCGroup priority="-1" includeLocationAISpawnTags="0" __type="SpawnDescription_NPCGroup">
              <autoSpawnSettings initialActivity="" minGroupSize="2" maxGroupSize="4" maxConcurrentSpawns="4" maxSpawns="8" minSpawnDelay="5" maxSpawnDelay="5" missionAlliedMarker="0" __type="AutoSpawnSettings">
                <positiveCharacterTags __type="TagList">
                  <tags>
                    <Reference value="50fccfb5-157f-401a-adaf-97406524f713" />
                    <Reference value="ecfb92fe-5d2d-4fef-aa8f-2f09fcf42b6f" />
                  </tags>
                </positiveCharacterTags>
                <negativeCharacterTags __type="TagList">
                  <tags />
                </negativeCharacterTags>
                <inventoryItems />
                <closetPositiveTags __type="TagList">
                  <tags />
                </closetPositiveTags>
                <closetNegativeTags __type="TagList">
                  <tags />
                </closetNegativeTags>
              </autoSpawnSettings>
              <identifierTags __type="TagList">
                <tags />
              </identifierTags>
            </SpawnDescription_NPCGroup>
            <SpawnDescription_NPCGroup priority="-1" includeLocationAISpawnTags="0" __type="SpawnDescription_NPCGroup">
              <autoSpawnSettings initialActivity="" minGroupSize="1" maxGroupSize="1" maxConcurrentSpawns="1" maxSpawns="2" minSpawnDelay="5" maxSpawnDelay="5" missionAlliedMarker="0" __type="AutoSpawnSettings">
                <positiveCharacterTags __type="TagList">
                  <tags>
                    <Reference value="ead9956c-0d00-4e7a-96f3-3b56f1386486" />
                    <Reference value="ecfb92fe-5d2d-4fef-aa8f-2f09fcf42b6f" />
                  </tags>
                </positiveCharacterTags>
                <negativeCharacterTags __type="TagList">
                  <tags />
                </negativeCharacterTags>
                <inventoryItems />
                <closetPositiveTags __type="TagList">
                  <tags />
                </closetPositiveTags>
                <closetNegativeTags __type="TagList">
                  <tags />
                </closetNegativeTags>
              </autoSpawnSettings>
              <identifierTags __type="TagList">
                <tags />
              </identifierTags>
            </SpawnDescription_NPCGroup>
            <SpawnDescription_NPCGroup priority="-1" includeLocationAISpawnTags="0" __type="SpawnDescription_NPCGroup">
              <autoSpawnSettings initialActivity="" minGroupSize="1" maxGroupSize="1" maxConcurrentSpawns="1" maxSpawns="2" minSpawnDelay="5" maxSpawnDelay="5" missionAlliedMarker="0" __type="AutoSpawnSettings">
                <positiveCharacterTags __type="TagList">
                  <tags>
                    <Reference value="016e2011-25c3-4a96-979d-8def1ab62003" />
                    <Reference value="ecfb92fe-5d2d-4fef-aa8f-2f09fcf42b6f" />
                  </tags>
                </positiveCharacterTags>
                <negativeCharacterTags __type="TagList">
                  <tags />
                </negativeCharacterTags>
                <inventoryItems />
                <closetPositiveTags __type="TagList">
                  <tags />
                </closetPositiveTags>
                <closetNegativeTags __type="TagList">
                  <tags />
                </closetNegativeTags>
              </autoSpawnSettings>
              <identifierTags __type="TagList">
                <tags />
              </identifierTags>
            </SpawnDescription_NPCGroup>
          </spawnDescriptions>
        </MissionPropertyValue_NPCSpawnDescriptions>
      </value>
    </MissionProperty>
    <MissionProperty missionVariableName="KickIfCSGained_BP" extendedTextToken="" __type="MissionProperty">
      <value>
        <MissionPropertyValue_Integer __type="BaseMissionPropertyValue" __polymorphicType="MissionPropertyValue_Integer">
          <options>
            <MissionPropertyValueOption_Integer textId="@LOC_UNINITIALIZED" weighting="1" DEBUG_forceChooseThisOption="0" value="1" variation="0" __type="BaseMissionPropertyValueOption" __polymorphicType="MissionPropertyValueOption_Integer">
              <dependentProperties />
            </MissionPropertyValueOption_Integer>
          </options>
        </MissionPropertyValue_Integer>
      </value>
    </MissionProperty>
  </properties>
</MissionBrokerEntry.PU_DestroyNarcotics_legal_Stanton4_H>