<SEntrancesDef.AEGS_Sabre_Raven __type="SEntrancesDef" __ref="85700a45-cb58-4565-aa87-e9b93e5d4fc8" __path="libs/foundry/records/ui/vehicleentrance/aegs_sabre_raven.xml">
  <boundingBoxScale x="1.6" y="1.6" z="1.6" __type="Vec3" />
  <boundingBoxOffset x="0" y="0" z="0" __type="Vec3" />
  <entranceArray>
    <SCEntranceItem entranceName="@entrance_canopy" jointName="canopy" shipState="Flying" __type="SCEntranceItem">
      <positionOffset x="0" y="-0.6" z="1.7" __type="Vec3" />
    </SCEntranceItem>
    <SCEntranceItem entranceName="@entrance_ladder" jointName="ladder_door" shipState="Grounded" __type="SCEntranceItem">
      <positionOffset x="-0.3" y="0.2" z="0" __type="Vec3" />
    </SCEntranceItem>
  </entranceArray>
</SEntrancesDef.AEGS_Sabre_Raven>