<WeaponProceduralAnimation.ksar_sniper_ballistic_01 __type="WeaponProceduralAnimation" __ref="973f255b-b227-43e2-b707-9f438b43f423" __path="libs/foundry/records/weaponproceduralanimation/ksar_sniper_ballistic_01.xml">
  <weaponProceduralClipsSetUp>
    <WeaponProceduralClipsSetUp filterByState="Jump" filterByMotionSpeed="Any" filterByPoseState="Any" filterByStanceState="Any" filterByAimStanceState="ADS" filterByLeanState="Any" filterByHeldItemType="Any" filterBySkeleton="Any" __type="ActorStateFilter" __polymorphicType="WeaponProceduralClipsSetUp">
      <weaponProceduralClips>
        <Reference value="2354d3ff-d48e-4c1f-8efc-2e26b4908791" />
      </weaponProceduralClips>
    </WeaponProceduralClipsSetUp>
    <WeaponProceduralClipsSetUp filterByState="Jump" filterByMotionSpeed="Any" filterByPoseState="Any" filterByStanceState="Any" filterByAimStanceState="Any" filterByLeanState="Any" filterByHeldItemType="Any" filterBySkeleton="Any" __type="ActorStateFilter" __polymorphicType="WeaponProceduralClipsSetUp">
      <weaponProceduralClips>
        <Reference value="0b1214d5-12d2-4d54-b221-01de98028290" />
      </weaponProceduralClips>
    </WeaponProceduralClipsSetUp>
    <WeaponProceduralClipsSetUp filterByState="Fall" filterByMotionSpeed="Any" filterByPoseState="Any" filterByStanceState="Any" filterByAimStanceState="ADS" filterByLeanState="Any" filterByHeldItemType="Any" filterBySkeleton="Any" __type="ActorStateFilter" __polymorphicType="WeaponProceduralClipsSetUp">
      <weaponProceduralClips>
        <Reference value="572642fc-a1b0-4b28-81e4-0fa25cb1b869" />
      </weaponProceduralClips>
    </WeaponProceduralClipsSetUp>
    <WeaponProceduralClipsSetUp filterByState="Fall" filterByMotionSpeed="Any" filterByPoseState="Any" filterByStanceState="Any" filterByAimStanceState="Any" filterByLeanState="Any" filterByHeldItemType="Any" filterBySkeleton="Any" __type="ActorStateFilter" __polymorphicType="WeaponProceduralClipsSetUp">
      <weaponProceduralClips>
        <Reference value="bc009b97-553b-491c-8380-4ea5a5553d1d" />
      </weaponProceduralClips>
    </WeaponProceduralClipsSetUp>
    <WeaponProceduralClipsSetUp filterByState="Any" filterByMotionSpeed="Idle" filterByPoseState="Any" filterByStanceState="Any" filterByAimStanceState="ADS" filterByLeanState="Any" filterByHeldItemType="Any" filterBySkeleton="Any" __type="ActorStateFilter" __polymorphicType="WeaponProceduralClipsSetUp">
      <weaponProceduralClips>
        <Reference value="49182404-e695-47cb-b5e3-b937bab7b90a" />
      </weaponProceduralClips>
    </WeaponProceduralClipsSetUp>
    <WeaponProceduralClipsSetUp filterByState="Any" filterByMotionSpeed="Idle" filterByPoseState="Any" filterByStanceState="Any" filterByAimStanceState="Any" filterByLeanState="Any" filterByHeldItemType="Any" filterBySkeleton="Any" __type="ActorStateFilter" __polymorphicType="WeaponProceduralClipsSetUp">
      <weaponProceduralClips>
        <Reference value="82211c65-192b-4fb7-9b1e-220221d12b7d" />
      </weaponProceduralClips>
    </WeaponProceduralClipsSetUp>
    <WeaponProceduralClipsSetUp filterByState="Any" filterByMotionSpeed="Any" filterByPoseState="Any" filterByStanceState="Any" filterByAimStanceState="ADS" filterByLeanState="Any" filterByHeldItemType="Any" filterBySkeleton="Any" __type="ActorStateFilter" __polymorphicType="WeaponProceduralClipsSetUp">
      <weaponProceduralClips>
        <Reference value="b6108e79-d123-439c-9f64-3a8eba2eff25" />
        <Reference value="d5eed025-6314-4cc3-8947-5468f31d216f" />
        <Reference value="6a9af09e-b358-41e8-927d-7c882e3354f0" />
      </weaponProceduralClips>
    </WeaponProceduralClipsSetUp>
    <WeaponProceduralClipsSetUp filterByState="Any" filterByMotionSpeed="Any" filterByPoseState="Any" filterByStanceState="Any" filterByAimStanceState="Any" filterByLeanState="Left" filterByHeldItemType="Any" filterBySkeleton="Any" __type="ActorStateFilter" __polymorphicType="WeaponProceduralClipsSetUp">
      <weaponProceduralClips>
        <Reference value="5df803ff-0f65-4726-891b-b77ab2eb3929" />
      </weaponProceduralClips>
    </WeaponProceduralClipsSetUp>
    <WeaponProceduralClipsSetUp filterByState="Any" filterByMotionSpeed="Any" filterByPoseState="Any" filterByStanceState="Any" filterByAimStanceState="Any" filterByLeanState="Right" filterByHeldItemType="Any" filterBySkeleton="Any" __type="ActorStateFilter" __polymorphicType="WeaponProceduralClipsSetUp">
      <weaponProceduralClips>
        <Reference value="14f8c1d6-2b62-41da-b18d-3794a1e59d4a" />
      </weaponProceduralClips>
    </WeaponProceduralClipsSetUp>
    <WeaponProceduralClipsSetUp filterByState="Any" filterByMotionSpeed="Any" filterByPoseState="Any" filterByStanceState="Any" filterByAimStanceState="Any" filterByLeanState="None" filterByHeldItemType="Any" filterBySkeleton="Any" __type="ActorStateFilter" __polymorphicType="WeaponProceduralClipsSetUp">
      <weaponProceduralClips>
        <Reference value="ad0be1ce-f593-496b-bcdf-1cd6bf209cc4" />
      </weaponProceduralClips>
    </WeaponProceduralClipsSetUp>
    <WeaponProceduralClipsSetUp filterByState="Interacting" filterByMotionSpeed="Any" filterByPoseState="Any" filterByStanceState="Any" filterByAimStanceState="Any" filterByLeanState="Any" filterByHeldItemType="Any" filterBySkeleton="Any" __type="ActorStateFilter" __polymorphicType="WeaponProceduralClipsSetUp">
      <weaponProceduralClips>
        <Reference value="a2927a9b-665e-4fb5-bcc6-375a8c35a9a1" />
      </weaponProceduralClips>
    </WeaponProceduralClipsSetUp>
    <WeaponProceduralClipsSetUp filterByState="Any" filterByMotionSpeed="Any" filterByPoseState="Any" filterByStanceState="Any" filterByAimStanceState="Ready" filterByLeanState="Any" filterByHeldItemType="Any" filterBySkeleton="Any" __type="ActorStateFilter" __polymorphicType="WeaponProceduralClipsSetUp">
      <weaponProceduralClips>
        <Reference value="197f6242-8faf-450f-832b-abe59a5b795a" />
        <Reference value="9d3fc905-71a0-471c-951e-3836d9515df7" />
        <Reference value="0399b80f-437e-4a89-9c47-afbdcfe1b784" />
        <Reference value="a47257e1-303d-4104-9edb-498aa92bcd2f" />
      </weaponProceduralClips>
    </WeaponProceduralClipsSetUp>
  </weaponProceduralClipsSetUp>
</WeaponProceduralAnimation.ksar_sniper_ballistic_01>